py2curl.py
py2curl-1.0.9.dist-info/LICENSE
py2curl-1.0.9.dist-info/METADATA
py2curl-1.0.9.dist-info/WHEEL
py2curl-1.0.9.dist-info/top_level.txt
py2curl-1.0.9.dist-info/RECORD
