Metadata-Version: 2.1
Name: py2curl
Version: 1.0.9
Summary: A tool render requests object to curl
Home-page: https://github.com/Hopetree/py2curl
Author: Hopetree
Author-email: zlwork2014@163.com
License: UNKNOWN
Keywords: python requests curl
Platform: UNKNOWN
Classifier: Operating System :: OS Independent
Classifier: Intended Audience :: Developers
Classifier: License :: OSI Approved :: MIT License
Classifier: Programming Language :: Python
